[
    {
        "titre": "Coding Shop",
        "intitule": "Vitrine de e-commerce",
        "image": "img/shop.jpg",
        "lien": "#coding",
        "id": "coding",
        "description": "Vitrine de e-commerce pour achat de cours en ligne de cours d'informatique réalisé lors d'un sprint autour du langage Javscript, afin d'avoir un premier aperçu de ce vaste langage.",
        "video": "video/codingShop.mp4",
        "img2": "img/next.png",
        "git": "https://github.com/elimf/CodingShop"
    },
    {
        "titre": "Weather App",
        "intitule": "Logiciels de filtres",
        "image": "img/meteo.png",
        "lien": "#meteo",
        "id": "meteo",
        "description": "Voici un",
        "video": "video/meteo.MP4",
        "img2": "img/next.png",
        "git": "https://github.com/elimf/Weather"
    },
    {
        "titre": "Jungle Store",
        "intitule": "Application Web",
        "image": "img/jungle.jpg",
        "lien": "#jungle",
        "id": "jungle",
        "description": "Je voulais découvrir un framework de Javascript j'ai donc suivi une formation OpenClassRoom pour voir les bases de React Js.",
        "video": "video/jungle.mp4",
        "img2": "img/next.png",
        "git": "https://github.com/elimf/Project-React"
    },
    {
        "titre": "Calculatrice",
        "intitule": "Application de calcul",
        "image": "img/calculatrice.jpg",
        "lien": "#calcul",
        "id": "calcul",
        "description": "Ce projet a été fait suite à une formation Javascript que j'ai suivi pour me familiarisé avec ce langage.",
        "video": "video/calcul.mp4",
        "img2": "img/next.png",
        "git": "https://github.com/elimf/Calculatrice"
    },
    {
        "titre": "SNEAKERS ADDICT",
        "intitule": "Site de vente de sneakers",
        "image": "img/sacai.jpeg",
        "lien": "#sneakers",
        "id": "sneakers",
        "description": "Le projet Sneakers Addict a été conçu pendant un sprint de Javascript Avancée en Vue Js.",
        "video": "vide",
        "img2": "img/next.png",
        "git": "https://github.com/elimf/SneakersAddict"
    },
    {
        "titre": "Instagram",
        "intitule": "Application ",
        "image": "img/insta.jpeg",
        "lien": "#insta",
        "id": "insta",
        "description": "Le projet Instagram était un projet que j'ai du effectuer lors d'un sprint autour du langage PHP en binôme avec un camarade.<br>Etant,très impliqué dans le projet j'ai décidé d'aller plus loin après la restitution du projet en ajoutant des fonctionnalités pour se rapprocher au maximun d'instagram.",
        "video": "vide",
        "img2": "img/next.png",
        "git": "https://github.com/elimf/Insta"
    }
    
]
